aladeen_clusterizer/ClusteringPipeline.py
aladeen_clusterizer/DailyClusteringPipeline.py
aladeen_clusterizer/MultiSentClusteringPipeline.py
aladeen_clusterizer/__init__.py
aladeen_clusterizer/abstract/ClusterScorer.py
aladeen_clusterizer/abstract/ClusteringAlgorithm.py
aladeen_clusterizer/abstract/DataPreprocessor.py
aladeen_clusterizer/abstract/EmbeddingGenerator.py
aladeen_clusterizer/abstract/OutlierDetector.py
aladeen_clusterizer/abstract/__init__.py
aladeen_clusterizer/cluster_scorers/CosineSimililarityClusterScorer.py
aladeen_clusterizer/cluster_scorers/SilhouetteClusterScorer.py
aladeen_clusterizer/cluster_scorers/__init__.py
aladeen_clusterizer/clustering_algorithms/HDBSCANClustering.py
aladeen_clusterizer/clustering_algorithms/KMeansClustering.py
aladeen_clusterizer/clustering_algorithms/__init__.py
aladeen_clusterizer/embedding_generators/SentenceTransformerEmbeddingGenerator.py
aladeen_clusterizer/embedding_generators/__init__.py
aladeen_clusterizer/misc/BenchmarkUtils.py
aladeen_clusterizer/misc/EmbeddingTimestamper.py
aladeen_clusterizer/misc/TextPreprocessor.py
aladeen_clusterizer/misc/__init__.py
aladeen_clusterizer/outlier_detectors/DynamicZScoreOutlierDetector.py
aladeen_clusterizer/outlier_detectors/IQROutlierDetector.py
aladeen_clusterizer/outlier_detectors/LOFOutlierDetector.py
aladeen_clusterizer/outlier_detectors/StandardDeviationOutlierDetector.py
aladeen_clusterizer/outlier_detectors/ZScoreOutlierDetector.py
aladeen_clusterizer/outlier_detectors/__init__.py
aladeen_clusterizer/result_visualizers/MultiResultVisualizer.py
aladeen_clusterizer/result_visualizers/ResultVisualizer.py
aladeen_clusterizer/result_visualizers/__init__.py
clusterizer_aladeen-0.3.0.dist-info/METADATA
clusterizer_aladeen-0.3.0.dist-info/WHEEL
clusterizer_aladeen-0.3.0.dist-info/RECORD
